fastlbp_imbg/__init__.py
fastlbp_imbg/_lbp.cp311-win_amd64.pyd
fastlbp_imbg/common.py
fastlbp_imbg/fastlbp.py
fastlbp_imbg/lbp.py
fastlbp_imbg/utils.py
fastlbp_imbg/workers.py
fastlbp_imbg-0.2.1.dist-info/LICENSE
fastlbp_imbg-0.2.1.dist-info/METADATA
fastlbp_imbg-0.2.1.dist-info/WHEEL
fastlbp_imbg-0.2.1.dist-info/top_level.txt
fastlbp_imbg-0.2.1.dist-info/RECORD
