Metadata-Version: 2.1
Name: fastlbp-imbg
Version: 0.2.1
Summary: Parallel multiradial LBP features
Author-email: Mykhailo Koreshkov <koreshov.m@gmail.com>
Project-URL: Homepage, https://github.com/imbg-ua/fastLBP
Project-URL: Bug Tracker, https://github.com/imbg-ua/fastLBP/issues
Keywords: lbp,texture,features,image processing,parallel
Classifier: Programming Language :: Python :: 3
Classifier: License :: OSI Approved :: MIT License
Classifier: Operating System :: OS Independent
Requires-Python: >=3.11
License-File: LICENSE
Requires-Dist: wheel
Requires-Dist: scikit-image>=0.22.0
Requires-Dist: numpy>=1.26.0
Requires-Dist: Pillow>=10.0.1
Requires-Dist: pandas>=2.1.1
Requires-Dist: psutil
